LICENSE
MANIFEST.in
README.md
setup.py
pyrfuniverse/__init__.py
pyrfuniverse/entry_points.py
pyrfuniverse.egg-info/PKG-INFO
pyrfuniverse.egg-info/SOURCES.txt
pyrfuniverse.egg-info/dependency_links.txt
pyrfuniverse.egg-info/entry_points.txt
pyrfuniverse.egg-info/requires.txt
pyrfuniverse.egg-info/top_level.txt
pyrfuniverse/attributes/__init__.py
pyrfuniverse/attributes/base_attr.py
pyrfuniverse/attributes/camera_attr.py
pyrfuniverse/attributes/cloth_attr.py
pyrfuniverse/attributes/collider_attr.py
pyrfuniverse/attributes/controller_attr.py
pyrfuniverse/attributes/custom_attr.py
pyrfuniverse/attributes/gameobject_attr.py
pyrfuniverse/attributes/light_attr.py
pyrfuniverse/attributes/pointcloud_attr.py
pyrfuniverse/attributes/rigidbody_attr.py
pyrfuniverse/controller/__init__.py
pyrfuniverse/controller/controller.py
pyrfuniverse/controller/jaco_controller.py
pyrfuniverse/controller/kinova_controller.py
pyrfuniverse/controller/stretch_controller.py
pyrfuniverse/controller/tobor_controller.py
pyrfuniverse/controller/ur5_controller.py
pyrfuniverse/envs/__init__.py
pyrfuniverse/envs/base_env.py
pyrfuniverse/envs/gym_wrapper_env.py
pyrfuniverse/grpc/RFUniverseGRPC_Server.py
pyrfuniverse/grpc/RFUniverseGRPC_pb2.py
pyrfuniverse/grpc/RFUniverseGRPC_pb2_grpc.py
pyrfuniverse/grpc/__init__.py
pyrfuniverse/utils/__init__.py
pyrfuniverse/utils/active_depth_generate.py
pyrfuniverse/utils/coordinate_system_converter.py
pyrfuniverse/utils/depth_processor.py
pyrfuniverse/utils/interpolate_utils.py
pyrfuniverse/utils/locker.py
pyrfuniverse/utils/os_utils.py
pyrfuniverse/utils/proc_wrapper.py
pyrfuniverse/utils/rfuniverse_communicator_base.py
pyrfuniverse/utils/rfuniverse_communicator_grpc.py
pyrfuniverse/utils/rfuniverse_communicator_tcp.py
pyrfuniverse/utils/rfuniverse_utility.py
pyrfuniverse/utils/version.py